handless/__init__.py
handless/_container.py
handless/_registry.py
handless/_utils.py
handless/exceptions.py
handless/lifetimes.py
handless/py.typed
handless-0.3.0.dist-info/METADATA
handless-0.3.0.dist-info/WHEEL
handless-0.3.0.dist-info/licenses/LICENSE
handless-0.3.0.dist-info/RECORD
