Metadata-Version: 2.4
Name: handless
Version: 0.3.0
Summary: A Python dependency injection container that automatically resolves and injects dependencies without polluting your code with framework-specific decorators. Inspired by Lagom, Svcs, and C# .NET DI, it keeps your code clean and flexible while offering multiple service registration options. 🚀
Project-URL: Homepage, https://github.com/g0di/handless
Project-URL: Documentation, https://github.com/g0di/handless
Project-URL: Source, https://github.com/g0di/handless
Project-URL: Changelog, https://github.com/g0di/handless/blob/main/CHANGELOG.md
Author-email: g0di <benoit.godard.p@gmail.com>
License: MIT License
License-File: LICENSE
Keywords: DI,IoC,dependency injection,dependency resolver,inversion of control,service container
Classifier: Development Status :: 4 - Beta
Classifier: Intended Audience :: Developers
Classifier: License :: OSI Approved :: MIT License
Classifier: Operating System :: OS Independent
Classifier: Programming Language :: Python :: 3 :: Only
Classifier: Programming Language :: Python :: 3.10
Classifier: Programming Language :: Python :: 3.11
Classifier: Programming Language :: Python :: 3.12
Classifier: Programming Language :: Python :: Implementation :: CPython
Classifier: Topic :: Software Development :: Libraries
Classifier: Topic :: Software Development :: Libraries :: Python Modules
Classifier: Topic :: Software Development :: Object Brokering
Classifier: Typing :: Typed
Requires-Python: >=3.10
